{
    "id": "polygon",
    "description": "Polygon is a protocol and a framework for building and connecting Ethereum-compatible blockchain networks. It aims to provide scalability solutions for Ethereum through the use of sidechains.",
    "tags": [
        "pos",
        "scaling solution",
        "ethereum ecosystem",
        "layer 2",
        "eip1559"
    ],
    "coin_details": {
        "name": "Polygon",
        "symbol": "MATIC",
        "logo": "logo/polygon.png",
        "max_supply": "∞"
    },
    "chain_details": [
        {
            "name": "Language",
            "type": "Solidity"
        },
        {
            "name": "Consensus",
            "type": "Proof of stake"
        },
        {
            "name": "Chain Layer",
            "type": "L2"
        },
        {
            "name": "Chain Type",
            "type": "EVM"
        }
    ],
    "official_links": {
        "website": "https://polygon.technology/",
        "whitepaper": "https://polygon.technology/whitepaper/",
        "documentation": "https://docs.polygon.technology/",
        "forum": "https://forum.polygon.technology/",
        "github": "https://github.com/maticnetwork"
    },
    "social_platforms": {
        "discord": "https://discord.gg/P5VBDBAx4X",
        "twitter": "https://twitter.com/0xPolygon",
        "reddit": "https://www.reddit.com/r/maticnetwork/",
        "community": "https://polygon.technology/community/",
        "coinmarketcap_community": "https://coinmarketcap.com/currencies/polygon/",
        "twitter_hashtag": "https://twitter.com/hashtag/maticnetwork"
    },
    "data_aggregator": [
        {
            "name": "CoinMarketCap",
            "url": "https://coinmarketcap.com/currencies/polygon/"
        },
        {
            "name": "CoinGecko",
            "url": "https://www.coingecko.com/en/coins/polygon"
        },
        {
            "name": "DefiLlama",
            "url": "https://defillama.com/chain/Matic"
        },
        {
            "name": "DappRadar",
            "url": "https://dappradar.com/chain/polygon"
        },
        {
            "name": "CryptoCompare",
            "url": "https://www.cryptocompare.com/coins/matic/overview"
        },
        {
            "name": "TradingView",
            "url": "https://www.tradingview.com/symbols/MATICUSD/"
        },
        {
            "name": "CoinDesk",
            "url": "https://www.coindesk.com/price/polygon-matic/"
        },
        {
            "name": "Investing",
            "url": "https://www.investing.com/crypto/polygon/eth-matic"
        },
        {
            "name": "MarketWatch",
            "url": "https://www.marketwatch.com/investing/cryptocurrency/maticusd"
        },
        {
            "name": "Yahoo Finance",
            "url": "https://finance.yahoo.com/quote/MATIC-USD"
        }
    ],
    "explorers": [
        {
            "name": "PolygonScan",
            "url": "https://polygonscan.com/"
        },
        {
            "name": "Polygon Explorer",
            "url": "https://explorer.polygon.technology/"
        },
        {
            "name": "Polygonscan Explorer",
            "url": "https://polygonscan.com/"
        },
        {
            "name": "Polygon Tracker",
            "url": "https://polygonscan.com/"
        },
        {
            "name": "Polygonscan",
            "url": "https://polygonscan.com/"
        },
        {
            "name": "Polygonscan",
            "url": "https://polygonscan.com/"
        },
        {
            "name": "Polygon Explorer",
            "url": "https://explorer.polygon.technology/"
        },
        {
            "name": "Matic Explorer",
            "url": "https://explorer-mainnet.maticvigil.com/"
        },
        {
            "name": "Matic Explorer",
            "url": "https://explorer-mainnet.maticvigil.com/"
        },
        {
            "name": "Matic Explorer",
            "url": "https://explorer-mainnet.maticvigil.com/"
        },
        {
            "name": "Matic Explorer",
            "url": "https://explorer-mainnet.maticvigil.com/"
        }
    ],
    "bridges": [
        {
            "name": "Polygon Bridge",
            "url": "https://wallet.matic.network/bridge/"
        },
        {
            "name": "Anyswap",
            "url": "https://anyswap.exchange/"
        },
        {
            "name": "PolyBridge",
            "url": "https://bridge.poly.network/"
        },
        {
            "name": "Matic Bridge",
            "url": "https://maticbridge.com/"
        },
        {
            "name": "Hop Protocol",
            "url": "https://hop.exchange/"
        },
        {
            "name": "Connext",
            "url": "https://connext.network/"
        }
    ],
    "bounty": [
        {
            "name": "Bug Bounty Program",
            "url": "https://polygon.technology/security/"
        }
    ],
    "grants": [
        {
            "name": "Polygon Grants",
            "url": "https://polygon.technology/grants/"
        }
    ],
    "faucets": [
        {
            "name": "Matic Network Faucet",
            "url": "https://faucet.matic.network/"
        },
        {
            "name": "PolyFaucet",
            "url": "https://faucet.poly-bridge.org/"
        },
        {
            "name": "All That Node",
            "url": "https://matic.supply/"
        },
        {
            "name": "Matic World",
            "url": "https://matic.supply/"
        }
    ],
    "rpcs": [
        {
            "name": "Polygon RPC",
            "url": "https://rpc-mainnet.maticvigil.com/"
        }
    ],
    "wallets": [
        {
            "name": "Polygon Wallet",
            "url": "https://wallet.matic.network/"
        },
        {
            "name": "Metamask",
            "url": "https://metamask.io/"
        },
        {
            "name": "Math Wallet",
            "url": "https://mathwallet.org/"
        },
        {
            "name": "Safe
